authclient/__init__.py
authclient/checkpassword.py
authserver/__init__.py
authserver/base_views.py
authserver/context_processors.py
authserver/gunicorn_conf.py
authserver/settings.py
authserver/urls.py
authserver/views.py
authserver/wsgi.py
authserver/static/mn.png
authserver/static/admin/js/jquery.init.js
authserver/static/vendor/select2/select2.full.min.js
authserver/static/vendor/select2/select2.min.css
authserver/static/vendor/select2/i18n/en.js
authserver/templates/admin/base_site.html
authserver/templates/oauth2_provider/authorize.html
authserver/templates/oauth2_provider/base.html
authserver/templates/oauth2_provider/unauthorized.html
authserver/templates/registration/base.html
authserver/templates/registration/login.html
authserver/vendor/__init__.py
authserver/vendor/django12factor/__init__.py
dockerauth/__init__.py
dockerauth/admin.py
dockerauth/jwtutils.py
dockerauth/models.py
dockerauth/permissions.py
dockerauth/views.py
dockerauth/management/__init__.py
dockerauth/management/commands/__init__.py
dockerauth/management/commands/dockerauth.py
dockerauth/migrations/0001_initial.py
dockerauth/migrations/0002_auto_20170709_2101.py
dockerauth/migrations/0003_remove_signkey_add_domain_fk.py
dockerauth/migrations/0004_find_domains_for_registries.py
dockerauth/migrations/0005_remove_dockerregistry_sign_key.py
dockerauth/migrations/0006_registry_require_domain_fk.py
dockerauth/migrations/__init__.py
mailauth/__init__.py
mailauth/admin.py
mailauth/apps.py
mailauth/auth.py
mailauth/forms.py
mailauth/models.py
mailauth/oauth2.py
mailauth/permissions.py
mailauth/utils.py
mailauth/views.py
mailauth/management/__init__.py
mailauth/management/commands/__init__.py
mailauth/management/commands/_common.py
mailauth/management/commands/domain.py
mailauth/management/commands/oauth2.py
mailauth/management/commands/permissions.py
mailauth/management/commands/spapi.py
mailauth/migrations/0001_initial.py
net.maurus.authserver-0.1.77.dist-info/DESCRIPTION.rst
net.maurus.authserver-0.1.77.dist-info/METADATA
net.maurus.authserver-0.1.77.dist-info/RECORD
net.maurus.authserver-0.1.77.dist-info/WHEEL
net.maurus.authserver-0.1.77.dist-info/entry_points.txt
net.maurus.authserver-0.1.77.dist-info/metadata.json
net.maurus.authserver-0.1.77.dist-info/top_level.txt
